{
  "_class": "shapeGroup",
  "clippingMaskMode": 0,
  "do_objectID": "0E561844-7104-4DC9-9356-490B9BB42A69",
  "exportOptions": {
    "_class": "exportOptions",
    "exportFormats": [
    ],
    "includedLayerIds": [
    ],
    "layerOptions": 0,
    "shouldTrim": false
  },
  "frame": {
    "_class": "rect",
    "constrainProportions": true,
    "height": 24,
    "width": 24,
    "x": 0,
    "y": 0
  },
  "hasClickThrough": false,
  "hasClippingMask": false,
  "isFlippedHorizontal": false,
  "isFlippedVertical": false,
  "isLocked": false,
  "isVisible": true,
  "layerListExpandedType": 0,
  "layers": [
    {
      "class": "rectangle",
      "id": "0BD3ABFE-350E-418A-8130-D79448B6AF7D"
    }
  ],
  "name": "Bounding Box",
  "nameIsFixed": true,
  "originalObjectID": "A8AA4C23-0B09-4127-B6E0-2EAEB2858B46",
  "resizingConstraint": 18,
  "resizingType": 2,
  "rotation": 0,
  "shouldBreakMaskChain": false,
  "style": {
    "sharedObjectID": "93CA5144-1D97-4262-BFA8-BB62D3C73233"
  },
  "userInfo": {
    "com.animaapp.stc-sketch-plugin": {
      "kModelPropertiesKey": {
      }
    }
  },
  "windingRule": 1
}